img_processor/__init__.py
img_processor/core.py
my_image_processor-0.1.0.dist-info/licenses/LICENSE
my_image_processor-0.1.0.dist-info/METADATA
my_image_processor-0.1.0.dist-info/WHEEL
my_image_processor-0.1.0.dist-info/top_level.txt
my_image_processor-0.1.0.dist-info/RECORD
