Metadata-Version: 2.4
Name: my_image_processor
Version: 0.1.0
Summary: Um pacote simples para processamento de imagens
Author: Seu Nome
Author-email: seu_email@exemplo.com
Classifier: Programming Language :: Python :: 3
Classifier: License :: OSI Approved :: MIT License
Classifier: Operating System :: OS Independent
Requires-Python: >=3.6
License-File: LICENSE
Requires-Dist: pillow
Dynamic: author
Dynamic: author-email
Dynamic: classifier
Dynamic: license-file
Dynamic: requires-dist
Dynamic: requires-python
Dynamic: summary
